pyAmizone.py
pyAmizone-0.0.1.dist-info/LICENSE.txt
pyAmizone-0.0.1.dist-info/METADATA
pyAmizone-0.0.1.dist-info/WHEEL
pyAmizone-0.0.1.dist-info/top_level.txt
pyAmizone-0.0.1.dist-info/RECORD
